{
  "ok": true,
  "data": {
    "items": [
      {
        "status": "\u5df2\u5b8c\u6210",
        "transfer": "in",
        "detail": "otc_authentication_deposit-\u8f6c\u5165",
        "currency": "BTC",
        "amount": "0.2",
        "time": "2019-06-26 15:46:36",
        "type": "\u5185\u90e8\u8f6c\u8d26",
        "id": 24585373
      },
      {
        "status": "\u5df2\u5b8c\u6210",
        "transfer": "out",
        "detail": "otc_authentication_deposit-\u8f6c\u51fa",
        "currency": "BTC",
        "amount": "0.2",
        "time": "2019-06-26 15:37:50",
        "type": "\u5185\u90e8\u8f6c\u8d26",
        "id": 24585372
      },
      {
        "status": "\u5df2\u5b8c\u6210",
        "transfer": "in",
        "detail": "otc_authentication_deposit-\u8f6c\u5165",
        "currency": "BTC",
        "amount": "0.2",
        "time": "2019-06-26 15:18:14",
        "type": "\u5185\u90e8\u8f6c\u8d26",
        "id": 24585369
      },
      {
        "status": "\u5df2\u5b8c\u6210",
        "transfer": "out",
        "detail": "otc_authentication_deposit-\u8f6c\u51fa",
        "currency": "BTC",
        "amount": "0.2",
        "time": "2019-06-26 15:01:43",
        "type": "\u5185\u90e8\u8f6c\u8d26",
        "id": 24585363
      },
      {
        "status": "\u5df2\u5b8c\u6210",
        "transfer": "in",
        "detail": "otc_authentication_deposit-\u8f6c\u5165",
        "currency": "BTC",
        "amount": "0.2",
        "time": "2019-06-26 14:42:37",
        "type": "\u5185\u90e8\u8f6c\u8d26",
        "id": 24585358
      },
      {
        "status": "\u5df2\u5b8c\u6210",
        "transfer": "out",
        "detail": "otc_authentication_deposit-\u8f6c\u51fa",
        "currency": "BTC",
        "amount": "0.2",
        "time": "2019-06-26 14:38:03",
        "type": "\u5185\u90e8\u8f6c\u8d26",
        "id": 24585357
      },
      {
        "status": "\u5df2\u5b8c\u6210",
        "transfer": "in",
        "detail": "\u573a\u5916\u4ea4\u6613-\u9000\u6b3e",
        "currency": "BTC",
        "amount": "0.1",
        "time": "2019-06-25 10:16:28",
        "type": "\u573a\u5916\u4ea4\u6613",
        "id": 24585272
      },
      {
        "status": "\u53d6\u6d88",
        "transfer": "out",
        "detail": "\u573a\u5916\u4ea4\u6613Ready to Pay flash_vendor\u7ed9 \u9633\u5149\u7537\u5b69",
        "currency": "BTC",
        "amount": "0.1",
        "time": "2019-06-25 10:01:26",
        "type": "\u573a\u5916\u4ea4\u6613",
        "id": 24585271
      },
      {
        "status": "\u5df2\u5b8c\u6210",
        "transfer": "in",
        "detail": "\u501f\u8d37-\u91ca\u653e\u8d28\u62bc\u7269",
        "currency": "BTC",
        "amount": "9.07426667",
        "time": "2019-06-19 17:02:50",
        "type": "\u501f\u8d37",
        "id": 24585166
      },
      {
        "status": "\u5df2\u5b8c\u6210",
        "transfer": "out",
        "detail": "\u501f\u8d37-\u8fd8\u6b3e",
        "currency": "USDT",
        "amount": "204.95175121",
        "time": "2019-06-19 17:02:50",
        "type": "\u501f\u8d37",
        "id": 24585165
      },
      {
        "status": "\u5df2\u5b8c\u6210",
        "transfer": "in",
        "detail": "\u573a\u5916\u4ea4\u6613-\u9000\u6b3e",
        "currency": "BTC",
        "amount": "0.2",
        "time": "2019-06-19 14:03:30",
        "type": "\u573a\u5916\u4ea4\u6613",
        "id": 24585147
      },
      {
        "status": "\u5df2\u5b8c\u6210",
        "transfer": "out",
        "detail": "\u573a\u5916\u4ea4\u6613Ready to Pay flash_vendor\u7ed9 Wang",
        "currency": "BTC",
        "amount": "0.3",
        "time": "2019-06-19 13:09:48",
        "type": "\u573a\u5916\u4ea4\u6613",
        "id": 24585145
      },
      {
        "status": "\u5df2\u5b8c\u6210",
        "transfer": "out",
        "detail": "\u573a\u5916\u4ea4\u6613Ready to Pay flash_vendor\u7ed9 Wang",
        "currency": "BTC",
        "amount": "0.2",
        "time": "2019-06-19 13:05:17",
        "type": "\u573a\u5916\u4ea4\u6613",
        "id": 24585144
      },
      {
        "status": "\u5df2\u5b8c\u6210",
        "transfer": "in",
        "detail": "\u573a\u5916\u4ea4\u6613-\u6536\u6b3e\u81ea Wang",
        "currency": "BTC",
        "amount": "0.1",
        "time": "2019-06-19 11:59:41",
        "type": "\u573a\u5916\u4ea4\u6613",
        "id": 24585140
      },
      {
        "status": "\u5df2\u5b8c\u6210",
        "transfer": "in",
        "detail": "\u573a\u5916\u4ea4\u6613-\u6536\u6b3e\u81ea Btw",
        "currency": "BTC",
        "amount": "0.18064267",
        "time": "2019-06-18 14:12:57",
        "type": "\u573a\u5916\u4ea4\u6613",
        "id": 24585121
      },
      {
        "status": "\u5df2\u5b8c\u6210",
        "transfer": "in",
        "detail": "\u573a\u5916\u4ea4\u6613-\u6536\u6b3e\u81ea Wang",
        "currency": "BTC",
        "amount": "0.099999",
        "time": "2019-06-18 12:06:49",
        "type": "\u573a\u5916\u4ea4\u6613",
        "id": 24585095
      },
      {
        "status": "\u5df2\u5b8c\u6210",
        "transfer": "out",
        "detail": "\u573a\u5916\u4ea4\u6613Ready to Pay flash_vendor\u7ed9 Wang",
        "currency": "ETH",
        "amount": "1",
        "time": "2019-06-18 11:45:12",
        "type": "\u573a\u5916\u4ea4\u6613",
        "id": 24585080
      },
      {
        "status": "\u5df2\u5b8c\u6210",
        "transfer": "in",
        "detail": "\u573a\u5916\u4ea4\u6613-\u9000\u6b3e",
        "currency": "BTC",
        "amount": "0.5",
        "time": "2019-06-18 11:09:44",
        "type": "\u573a\u5916\u4ea4\u6613",
        "id": 24585059
      },
      {
        "status": "\u53d6\u6d88",
        "transfer": "out",
        "detail": "\u573a\u5916\u4ea4\u6613Ready to Pay flash_vendor\u7ed9 Wang",
        "currency": "BTC",
        "amount": "0.5",
        "time": "2019-06-18 10:54:41",
        "type": "\u573a\u5916\u4ea4\u6613",
        "id": 24585057
      },
      {
        "status": "\u5df2\u5b8c\u6210",
        "transfer": "in",
        "detail": "\u573a\u5916\u4ea4\u6613-\u9000\u6b3e",
        "currency": "BTC",
        "amount": "0.1",
        "time": "2019-06-17 19:17:08",
        "type": "\u573a\u5916\u4ea4\u6613",
        "id": 24585049
      }
    ],
    "total": 238,
    "page": 1,
    "page_size": 20
  }
}
